speedwagon/__init__.py
speedwagon/__main__.py
speedwagon/exceptions.py
speedwagon/favicon.ico
speedwagon/hookspecs.py
speedwagon/info.py
speedwagon/job.py
speedwagon/logo.png
speedwagon/plugin_hook.py
speedwagon/plugins.py
speedwagon/py.typed
speedwagon/reports.py
speedwagon/runner.py
speedwagon/runner_strategies.py
speedwagon/startup.py
speedwagon/utils.py
speedwagon/validators.py
speedwagon/worker.py
speedwagon/workflow.py
speedwagon/config/__init__.py
speedwagon/config/common.py
speedwagon/config/config.py
speedwagon/config/plugins.py
speedwagon/config/tabs.py
speedwagon/config/workflow.py
speedwagon/frontend/__init__.py
speedwagon/frontend/interaction.py
speedwagon/frontend/reporter.py
speedwagon/frontend/cli/__init__.py
speedwagon/frontend/cli/user_interaction.py
speedwagon/frontend/qtwidgets/__init__.py
speedwagon/frontend/qtwidgets/gui.py
speedwagon/frontend/qtwidgets/gui_startup.py
speedwagon/frontend/qtwidgets/logging_helpers.py
speedwagon/frontend/qtwidgets/runners.py
speedwagon/frontend/qtwidgets/shared_custom_widgets.py
speedwagon/frontend/qtwidgets/splashscreen.py
speedwagon/frontend/qtwidgets/tabs.py
speedwagon/frontend/qtwidgets/ui_loader.py
speedwagon/frontend/qtwidgets/user_interaction.py
speedwagon/frontend/qtwidgets/widgets.py
speedwagon/frontend/qtwidgets/worker.py
speedwagon/frontend/qtwidgets/dialog/__init__.py
speedwagon/frontend/qtwidgets/dialog/dialogs.py
speedwagon/frontend/qtwidgets/dialog/settings.py
speedwagon/frontend/qtwidgets/models/__init__.py
speedwagon/frontend/qtwidgets/models/common.py
speedwagon/frontend/qtwidgets/models/options.py
speedwagon/frontend/qtwidgets/models/plugins.py
speedwagon/frontend/qtwidgets/models/settings.py
speedwagon/frontend/qtwidgets/models/tabs.py
speedwagon/frontend/qtwidgets/models/workflows.py
speedwagon/frontend/qtwidgets/ui/__init__.py
speedwagon/frontend/qtwidgets/ui/console.ui
speedwagon/frontend/qtwidgets/ui/create_job_tab.ui
speedwagon/frontend/qtwidgets/ui/main_window.ui
speedwagon-0.4.0b10.dist-info/LICENSE
speedwagon-0.4.0b10.dist-info/METADATA
speedwagon-0.4.0b10.dist-info/WHEEL
speedwagon-0.4.0b10.dist-info/entry_points.txt
speedwagon-0.4.0b10.dist-info/top_level.txt
speedwagon-0.4.0b10.dist-info/RECORD
