Metadata-Version: 2.1
Name: speedwagon
Version: 0.4.0b10
Summary: Collection of tools and workflows for DS
Author-email: "University Library at The University of Illinois at Urbana Champaign: Preservation Services" <prescons@library.illinois.edu>
Maintainer-email: Henry Borchers <hborcher@illinois.edu>
License: University of Illinois/NCSA Open Source License
Project-URL: project, https://www.library.illinois.edu/dccdocs/speedwagon
Project-URL: download, https://github.com/UIUCLibrary/Speedwagon/releases
Keywords: GUI
Classifier: Development Status :: 4 - Beta
Classifier: Intended Audience :: End Users/Desktop
Classifier: Natural Language :: English
Classifier: Programming Language :: Python :: 3.9
Classifier: License :: OSI Approved :: University of Illinois/NCSA Open Source License
Classifier: Operating System :: MacOS
Classifier: Operating System :: Microsoft :: Windows
Classifier: Operating System :: POSIX :: Linux
Requires-Python: >=3.9
License-File: LICENSE
Requires-Dist: pyyaml
Requires-Dist: importlib-metadata; python_version < "3.10"
Requires-Dist: typing-extensions; python_version < "3.11"
Requires-Dist: lxml
Requires-Dist: requests
Requires-Dist: pluggy>=1.0
Provides-Extra: qt
Requires-Dist: PySide6~=6.8; extra == "qt"
